plotting3dprinter/__init__.py
plotting3dprinter/raycaster.py
plotting3dprinter/svg_interpreter.py
plotting3dprinter/svg_to_gcode.py
plotting3dprinter/svgto3dprintplot_cmd.py
plotting3dprinter/version.py
plotting3dprinter-1.12.dist-info/METADATA
plotting3dprinter-1.12.dist-info/WHEEL
plotting3dprinter-1.12.dist-info/entry_points.txt
plotting3dprinter-1.12.dist-info/top_level.txt
plotting3dprinter-1.12.dist-info/RECORD
