Metadata-Version: 2.1
Name: plotting3dprinter
Version: 1.12
Summary: Generate gcode to plot on a 3d printer with a pen
Home-page: https://github.com/BuysDB/plotting3dprinter
Author: Buys de Barbanson
Author-email: aegit@buysdb.nl
License: MIT
Classifier: Development Status :: 3 - Alpha
Classifier: Intended Audience :: Science/Research
Classifier: Programming Language :: Python :: 3.6
Classifier: Programming Language :: Python :: 3.7
Classifier: License :: OSI Approved :: MIT License
Requires-Dist: numpy (>=1.16.5)
Requires-Dist: lxml
